qoqo_qir-0.3.0.dist-info/METADATA
qoqo_qir-0.3.0.dist-info/WHEEL
qoqo_qir-0.3.0.dist-info/licenses/LICENSE
qoqo_qir/DEPENDENCIES
qoqo_qir/__init__.py
qoqo_qir/qoqo_qir.cp311-win_amd64.pyd
qoqo_qir/qoqo_qir.pyi
qoqo_qir-0.3.0.dist-info/RECORD
